fluid/__init__.py
fluid/helpers.py
fluid/network.py
fluid_jsonrpc-0.0.1.dist-info/METADATA
fluid_jsonrpc-0.0.1.dist-info/WHEEL
fluid_jsonrpc-0.0.1.dist-info/top_level.txt
fluid_jsonrpc-0.0.1.dist-info/RECORD
