Metadata-Version: 2.1
Name: fluid-jsonrpc
Version: 0.0.1
Summary: UNKNOWN
Home-page: https://github.com/blinktrade/fluid-jsonrpc
Author: Blinktrade
License: BSD
Platform: UNKNOWN
Requires-Dist: requests
